setup.py
ga_utils/__init__.py
ga_utils/main.py
ga_utils.egg-info/PKG-INFO
ga_utils.egg-info/SOURCES.txt
ga_utils.egg-info/dependency_links.txt
ga_utils.egg-info/entry_points.txt
ga_utils.egg-info/requires.txt
ga_utils.egg-info/top_level.txt