Metadata-Version: 2.1
Name: ga-utils
Version: 0.0.9
Summary: 通过GA协议获取数据，用于调试GA控件树
Home-page: https://git.woa.com/janeajian/ga-util
Author: janeluck
Author-email: janeluck158@outlook.com
License: MIT
Platform: UNKNOWN
Classifier: Programming Language :: Python :: 3
Classifier: License :: OSI Approved :: MIT License
Classifier: Operating System :: OS Independent
